alo/__init__.py
alo/cli.py
alo-0.3.0.dist-info/entry_points.txt
alo-0.3.0.dist-info/LICENSE
alo-0.3.0.dist-info/WHEEL
alo-0.3.0.dist-info/METADATA
alo-0.3.0.dist-info/RECORD
