Metadata-Version: 2.1
Name: alo
Version: 0.3.0
Summary: A tool to combine function with DAG
Home-page: https://github.com/uchuhimo/alo
License: Apache-2.0
Author: uchuhimo
Author-email: uchuhimo@outlook.com
Requires-Python: >=3.6
Classifier: Development Status :: 2 - Pre-Alpha
Classifier: Intended Audience :: Developers
Classifier: License :: OSI Approved :: Apache Software License
Classifier: Natural Language :: English
Classifier: Programming Language :: Python :: 3
Classifier: Programming Language :: Python :: 3.6
Classifier: Programming Language :: Python :: 3.7
Classifier: Programming Language :: Python :: 3.8
Requires-Dist: click
Requires-Dist: contextvars; python_version < "3.7"
Requires-Dist: dataclasses; python_version < "3.7"
Requires-Dist: more-itertools
Requires-Dist: six
Requires-Dist: typing-extensions
Requires-Dist: typing; python_version < "3.7"
Project-URL: Repository, https://github.com/uchuhimo/alo
